pandasy/__init__.py
pandasy/dummy.py
pandasy_version/__init__.py
tests/__init__.py
tests/pandasy/__init__.py
tests/pandasy/test_dummy.py
slide-0.0.2.dist-info/LICENSE
slide-0.0.2.dist-info/LICENSE copy
slide-0.0.2.dist-info/METADATA
slide-0.0.2.dist-info/WHEEL
slide-0.0.2.dist-info/top_level.txt
slide-0.0.2.dist-info/RECORD
