Metadata-Version: 2.1
Name: slide
Version: 0.0.2
Summary: A collection of utility functions to unify pandas-like dataframes behaviors
Home-page: http://github.com/fugue-project/pandasy
Author: Han Wang
Author-email: goodwanghan@gmail.com
License: Apache-2.0
Keywords: pandas sql
Platform: UNKNOWN
Classifier: Development Status :: 3 - Alpha
Classifier: Intended Audience :: Developers
Classifier: Topic :: Software Development :: Libraries :: Python Modules
Classifier: License :: OSI Approved :: Apache Software License
Classifier: Programming Language :: Python :: 3.6
Classifier: Programming Language :: Python :: 3.7
Classifier: Programming Language :: Python :: 3.8
Classifier: Programming Language :: Python :: 3 :: Only
Requires-Python: >=3.6
Requires-Dist: triad
Requires-Dist: pandas (>=1.1.0)
Requires-Dist: numpy (>=1.19)
Provides-Extra: all
Requires-Dist: dask[dataframe] ; extra == 'all'
Requires-Dist: cloudpickle (>=1.4.0) ; extra == 'all'
Requires-Dist: modin[ray] ; extra == 'all'
Provides-Extra: dask
Requires-Dist: dask[dataframe] ; extra == 'dask'
Requires-Dist: cloudpickle (>=1.4.0) ; extra == 'dask'
Provides-Extra: ray
Requires-Dist: pandas (>=1.1.2) ; extra == 'ray'
Requires-Dist: modin[ray] (>=0.8.1.1) ; extra == 'ray'
